{
  "current": [
    {
      "visible": true,
      "category": "🎓 Research Project",
      "title": "Text-To-Robot",
      "description": "...",
      "tags": ["AWS"],
      "image": {
        "src": "",
        "alt": "overview",
        "linkTo": ""
      },
      "links": [
        {
          "type": "github",
          "url": "https://github.com/nemonemonee/"
        },
        {
          "type": "external",
          "url": ""
        }
      ]
    },
    {
      "visible": true,
      "category": "🎓 Research Project",
      "title": "Freeform",
      "description": "...",
      "tags": ["NLP"],
      "image": {
        "src": "",
        "alt": "overview",
        "linkTo": ""
      },
      "links": [
        {
          "type": "github",
          "url": "https://github.com/nemonemonee/"
        },
        {
          "type": "external",
          "url": ""
        }
      ]
    }
  ]
}
